{"title":"Luan Santana - Meteoro [Ao Vivo][2009-2010] - Floresta","uid":5608516,"size":98700185,"categoryP":"audio","categoryS":"music","magnet":"?xt=urn:btih:00e94317713928071714877ee780b0b298c64aed&amp;dn=Luan+Santana+-+Meteoro+%5BAo+Vivo%5D%5B2009-2010%5D+-+Floresta&amp;tr=udp%3A%2F%2Ftracker.openbittorrent.com%3A80&amp;tr=udp%3A%2F%2Fopen.demonii.com%3A1337&amp;tr=udp%3A%2F%2Ftracker.coppersurfer.tk%3A6969&amp;tr=udp%3A%2F%2Fexodus.desync.com%3A6969","seeders":2,"leechers":1,"uploader":"Floresta","files":18,"time":1275715439,"description":"CD Luan Santana - Meteoro Ao Vivo \n\n\n # DescriÃƒÂ§ÃƒÂ£o: [description]\n\n\nCom apenas 18 anos de idade, o cantor Luan Santana, mais conhecido como &quot;Gurizinho&quot;, tem uma agenda lotada e um currÃƒÂ­culo que inclui apresentaÃƒÂ§ÃƒÂµes em vÃƒÂ¡rios estados e eventos nacionais importantes, incluindo a &quot;Festa de PeÃƒÂ£o de Barretos&quot;. Como se nÃƒÂ£o bastasse tudo isso, o garoto prodÃƒÂ­gio da mÃƒÂºsica sertaneja lanÃƒÂ§a este ÃƒÂ¡lbum ao vivo fantÃƒÂ¡stico, gravado em sua cidade natal, Campo Grande. No repertÃƒÂ³rio, canÃƒÂ§ÃƒÂµes inÃƒÂ©ditas e as mÃƒÂºsicas mais famosas do seu disco anterior. ImperdÃƒÂ­vel!\n\n\n # Description:\n\nWith only 18 years old, the singer Luan Santana, better known as &quot;Gurizinho&quot; has a busy schedule and a curriculum that includes presentations on various important state and national events, including the &quot;Festival of The Barretos. &quot; As if in all this enough, the boy's music prodgio sertaneja Country. this fantastic live album, recorded in his hometown of Campo Grande. In the repertoire, songs and indites musics most famous of his previous album. enjoy!!!\n\n\n\n\n # Artista:[artist] Luan Santana\n # Ano: [year] 2009 / 2010\n # ProcedÃƒÂªncia: [country] Brasil,Brazil,Nacional\n # Gravadora: [Label]: Sony &amp; BMG \n # Arquivo: [file] Mp3 \n # Bits: 224 Kbps\n # RefeRÃƒÂªncia: [reference] Sertanejo,Country,Portugual,LÃƒÂ­ngua Portuguesa,Samba,Brazilian Music.\n\n\n\n # Disco: [Tracks]\n\n \n   \t1. Meteoro\n\t2. VocÃƒÂª NÃƒÂ£o Sabe o que ÃƒÂ© Amor\n\t3. Sinais\n\t4. To de Cara\n\t5. Aqui ÃƒÂ© o Seu Lugar/ Digitais\n\t6. Minha Boca VocÃƒÂª NÃƒÂ£o Beija Mais\n\t7. Jogo do Amor\n\t8. Vou Voar\n\t9. Sempre com VocÃƒÂª\n\t10. Eu to Jogando Verde\n\t11. Sobrenatural\n\t12. Apaixonado / a Loira do Carro Branco\n\t13. Pra VocÃƒÂª Lembrar de Mim\n\t14. VocÃƒÂª do Meu Lado\n\t15. A Louca\n\t16. Chocolate\n\t17. Amigos Pela FÃƒÂ©\n\n\nFloresta 2010\n\n ","torrent":{"xt":"urn:btih:00e94317713928071714877ee780b0b298c64aed","amp;dn":"Luan+Santana+-+Meteoro+%5BAo+Vivo%5D%5B2009-2010%5D+-+Floresta","amp;tr":["udp%3A%2F%2Ftracker.openbittorrent.com%3A80","udp%3A%2F%2Fopen.demonii.com%3A1337","udp%3A%2F%2Ftracker.coppersurfer.tk%3A6969","udp%3A%2F%2Fexodus.desync.com%3A6969"],"infoHash":"00e94317713928071714877ee780b0b298c64aed","infoHashBuffer":{"type":"Buffer","data":[0,233,67,23,113,57,40,7,23,20,135,126,231,128,176,178,152,198,74,237]},"announce":[],"urlList":[]}}