{"title":"NCH.Express.Talk.Business.v4.26-LAXiTY","uid":7079256,"size":666478,"categoryP":"applications","categoryS":"windows","magnet":"?xt=urn:btih:07ac02ea9e15da8f2d58c8b32cb4cdded9dd7807&amp;dn=NCH.Express.Talk.Business.v4.26-LAXiTY&amp;tr=udp%3A%2F%2Ftracker.openbittorrent.com%3A80&amp;tr=udp%3A%2F%2Fopen.demonii.com%3A1337&amp;tr=udp%3A%2F%2Ftracker.coppersurfer.tk%3A6969&amp;tr=udp%3A%2F%2Fexodus.desync.com%3A6969","seeders":2,"leechers":0,"uploader":"scene4all","files":-1,"time":1330967110,"description":"---------------------------------------------------------------------------------\n                                                                                 \n           SSSSSSSSSSSSSSS       444444444                 AAA                   \n         SS:::::::::::::::S     4::::::::4                A:::A                  \n        S:::::SSSSSS::::::S    4:::::::::4               A:::::A                 \n        S:::::S     SSSSSSS   4::::44::::4              A:::::::A                \n        S:::::S              4::::4 4::::4             A:::::::::A               \n        S:::::S             4::::4  4::::4            A:::::A:::::A              \n         S::::SSSS         4::::4   4::::4           A:::::A A:::::A             \n          SS::::::SSSSS   4::::444444::::444        A:::::A   A:::::A            \n            SSS::::::::SS 4::::::::::::::::4       A:::::A     A:::::A           \n               SSSSSS::::S4444444444:::::444      A:::::AAAAAAAAA:::::A          \n                    S:::::S         4::::4       A:::::::::::::::::::::A         \n                    S:::::S         4::::4      A:::::AAAAAAAAAAAAA:::::A        \n        SSSSSSS     S:::::S         4::::4     A:::::A             A:::::A       \n        S::::::SSSSSS:::::S       44::::::44  A:::::A               A:::::A      \n        S:::::::::::::::SS        4::::::::4 A:::::A                 A:::::A     \n         SSSSSSSSSSSSSSS          4444444444AAAAAAA                   AAAAAAA    \n                                                                                 \n                                                                                 \n---------------------------------------------------------------------------------\n\n                      NCH.Express.Talk.Business.v4.26-LAXiTY                     \n\n---------------------------------------------------------------------------------\n\nR E L E A S E . N O T E S\n\nExpress Talk is a VoIP softphone that allows you to talk\nfrom your PC to any other PC with a softphone. It uses the\nSIP protocol and is compatible with most major VoIP SIP\nservice providers.\n\ni N S T A L L . N O T E S\n\nLook in &quot;ser.no.txt&quot;.\n\n---------------------------------------------------------------------------------","torrent":{"xt":"urn:btih:07ac02ea9e15da8f2d58c8b32cb4cdded9dd7807","amp;dn":"NCH.Express.Talk.Business.v4.26-LAXiTY","amp;tr":["udp%3A%2F%2Ftracker.openbittorrent.com%3A80","udp%3A%2F%2Fopen.demonii.com%3A1337","udp%3A%2F%2Ftracker.coppersurfer.tk%3A6969","udp%3A%2F%2Fexodus.desync.com%3A6969"],"infoHash":"07ac02ea9e15da8f2d58c8b32cb4cdded9dd7807","infoHashBuffer":{"type":"Buffer","data":[7,172,2,234,158,21,218,143,45,88,200,179,44,180,205,222,217,221,120,7]},"announce":[],"urlList":[]}}