{"title":"21 FOOT ART - Lina Napoli - Hands And Feet Above The Rest HD 720","uid":8654430,"size":1140829348,"categoryP":"porn","categoryS":"hd___movies","magnet":"?xt=urn:btih:0da57d07cb0e0ce22d49cb089e8fdfb2bfb96d3b&amp;dn=21+FOOT+ART+-+Lina+Napoli+-+Hands+And+Feet+Above+The+Rest+HD+720&amp;tr=udp%3A%2F%2Ftracker.openbittorrent.com%3A80&amp;tr=udp%3A%2F%2Fopen.demonii.com%3A1337&amp;tr=udp%3A%2F%2Ftracker.coppersurfer.tk%3A6969&amp;tr=udp%3A%2F%2Fexodus.desync.com%3A6969","seeders":2,"leechers":1,"uploader":"beta2008x","files":1,"time":1373180288,"description":" &lt;a href=&quot;http://imgboxxx.com/viewer.php?file=3fk81_21fa_lina_napoli_720.jpg&quot; rel=&quot;nofollow&quot; target=&quot;_NEW&quot;&gt;http://imgboxxx.com/viewer.php?file=3fk81_21fa_lina_napoli_720.jpg&lt;/a&gt;\n\n","torrent":{"xt":"urn:btih:0da57d07cb0e0ce22d49cb089e8fdfb2bfb96d3b","amp;dn":"21+FOOT+ART+-+Lina+Napoli+-+Hands+And+Feet+Above+The+Rest+HD+720","amp;tr":["udp%3A%2F%2Ftracker.openbittorrent.com%3A80","udp%3A%2F%2Fopen.demonii.com%3A1337","udp%3A%2F%2Ftracker.coppersurfer.tk%3A6969","udp%3A%2F%2Fexodus.desync.com%3A6969"],"infoHash":"0da57d07cb0e0ce22d49cb089e8fdfb2bfb96d3b","infoHashBuffer":{"type":"Buffer","data":[13,165,125,7,203,14,12,226,45,73,203,8,158,143,223,178,191,185,109,59]},"announce":[],"urlList":[]}}