{"title":"Free PLR - 32 free private label rights and what to do with them","uid":5256010,"size":266240,"categoryP":"other","categoryS":"e_books","magnet":"?xt=urn:btih:0f51d23a0e2396065f73dfa511101b879a77896e&amp;dn=Free+PLR+-+32+free+private+label+rights+and+what+to+do+with+them&amp;tr=udp%3A%2F%2Ftracker.openbittorrent.com%3A80&amp;tr=udp%3A%2F%2Fopen.demonii.com%3A1337&amp;tr=udp%3A%2F%2Ftracker.coppersurfer.tk%3A6969&amp;tr=udp%3A%2F%2Fexodus.desync.com%3A6969","seeders":2,"leechers":0,"uploader":"8eVe8","files":1,"time":1262551310,"description":"32 free private label rights ebooks and tips on what to do with them.","torrent":{"xt":"urn:btih:0f51d23a0e2396065f73dfa511101b879a77896e","amp;dn":"Free+PLR+-+32+free+private+label+rights+and+what+to+do+with+them","amp;tr":["udp%3A%2F%2Ftracker.openbittorrent.com%3A80","udp%3A%2F%2Fopen.demonii.com%3A1337","udp%3A%2F%2Ftracker.coppersurfer.tk%3A6969","udp%3A%2F%2Fexodus.desync.com%3A6969"],"infoHash":"0f51d23a0e2396065f73dfa511101b879a77896e","infoHashBuffer":{"type":"Buffer","data":[15,81,210,58,14,35,150,6,95,115,223,165,17,16,27,135,154,119,137,110]},"announce":[],"urlList":[]}}