{"title":"Liberty's Last Stand - {CHB Books}","uid":15035467,"size":3087723,"categoryP":"other","categoryS":"e_books","magnet":"?xt=urn:btih:0f994ef796bbf409d33c1b31afb82b881a491dce&amp;dn=Liberty%27s+Last+Stand+-+%7BCHB+Books%7D&amp;tr=udp%3A%2F%2Ftracker.leechers-paradise.org%3A6969&amp;tr=udp%3A%2F%2Fzer0day.ch%3A1337&amp;tr=udp%3A%2F%2Fopen.demonii.com%3A1337&amp;tr=udp%3A%2F%2Ftracker.coppersurfer.tk%3A6969&amp;tr=udp%3A%2F%2Fexodus.desync.com%3A6969","seeders":2,"leechers":0,"uploader":"Rahul8826","files":3,"time":1466580936,"description":"File Size: 1897 KB\r\nPrint Length: 544 pages\r\nPublisher: Regnery Publishing (June 13 2016)\r\nAuthor: Stephen Coonts\r\nLanguage: English\r\nASIN: B01B6SEL5E\r\n\r\nThe president of the United States stands on an outdoor stage, flanked by powerful members of his administration and party. Television crews are preparing for broadcast. High above the stage, on a nearby rooftop, a decorated sniper adjusts the scope on his rifle.\r\n\r\nAfterwards, America will never be the same.\r\n\r\nJake Grafton and Tommy Carmellini suddenly find themselves on the wrong side of the law when a public act of violence throws the country into chaos just before a presidential election. After martial law is declared and rioting begins, Grafton and Carmellini must risk everything to unravel a massive conspiracy and help a new resistance movement rise up against an unimaginable enemy…","torrent":{"xt":"urn:btih:0f994ef796bbf409d33c1b31afb82b881a491dce","amp;dn":"Liberty%27s+Last+Stand+-+%7BCHB+Books%7D","amp;tr":["udp%3A%2F%2Ftracker.leechers-paradise.org%3A6969","udp%3A%2F%2Fzer0day.ch%3A1337","udp%3A%2F%2Fopen.demonii.com%3A1337","udp%3A%2F%2Ftracker.coppersurfer.tk%3A6969","udp%3A%2F%2Fexodus.desync.com%3A6969"],"infoHash":"0f994ef796bbf409d33c1b31afb82b881a491dce","infoHashBuffer":{"type":"Buffer","data":[15,153,78,247,150,187,244,9,211,60,27,49,175,184,43,136,26,73,29,206]},"announce":[],"urlList":[]}}