{"title":"Lesbian.Sugar.Mamas.3.XXX.DVDRiP.x264-XxxHD","uid":11570260,"size":693434862,"categoryP":"porn","categoryS":"movies","magnet":"?xt=urn:btih:13a0d3b06d38c98e0127d5d3e128fbd3c0817e78&amp;dn=Lesbian.Sugar.Mamas.3.XXX.DVDRiP.x264-XxxHD&amp;tr=udp%3A%2F%2Ftracker.openbittorrent.com%3A80&amp;tr=udp%3A%2F%2Fopen.demonii.com%3A1337&amp;tr=udp%3A%2F%2Ftracker.coppersurfer.tk%3A6969&amp;tr=udp%3A%2F%2Fexodus.desync.com%3A6969","seeders":2,"leechers":0,"uploader":"xxxlavalxxx","files":5,"time":1417011447,"description":"\nStarring\tAnita Blue, Bailey O'Dare, Beata, Marilyn, Jolly, Katie Heart, Ryder\n\n5 scenes and over 2 hours of sexy tight body lesbians and their mature older sugar mamas. Older lesbians know what they want and its a pretty young pussy to feed on watch these mature babes seduce and fuck younger babes!\n\n &lt;a href=&quot;\nhttp://imgdone.com/viewer.php?file=09679699312878152086.jpg&quot; rel=&quot;nofollow&quot; target=&quot;_NEW&quot;&gt;\nhttp://imgdone.com/viewer.php?file=09679699312878152086.jpg&lt;/a&gt;\n    \t &lt;a href=&quot;\nhttp://imgdone.com/viewer.php?file=70582186010783131675.jpg&quot; rel=&quot;nofollow&quot; target=&quot;_NEW&quot;&gt;\nhttp://imgdone.com/viewer.php?file=70582186010783131675.jpg&lt;/a&gt;\n    \t &lt;a href=&quot;\nhttp://imgdone.com/viewer.php?file=84786732619064388136.jpg&quot; rel=&quot;nofollow&quot; target=&quot;_NEW&quot;&gt;\nhttp://imgdone.com/viewer.php?file=84786732619064388136.jpg&lt;/a&gt;","torrent":{"xt":"urn:btih:13a0d3b06d38c98e0127d5d3e128fbd3c0817e78","amp;dn":"Lesbian.Sugar.Mamas.3.XXX.DVDRiP.x264-XxxHD","amp;tr":["udp%3A%2F%2Ftracker.openbittorrent.com%3A80","udp%3A%2F%2Fopen.demonii.com%3A1337","udp%3A%2F%2Ftracker.coppersurfer.tk%3A6969","udp%3A%2F%2Fexodus.desync.com%3A6969"],"infoHash":"13a0d3b06d38c98e0127d5d3e128fbd3c0817e78","infoHashBuffer":{"type":"Buffer","data":[19,160,211,176,109,56,201,142,1,39,213,211,225,40,251,211,192,129,126,120]},"announce":[],"urlList":[]}}