{"title":"another super mario bros wbfs","uid":7976776,"size":599785472,"categoryP":"games","categoryS":"wii","magnet":"?xt=urn:btih:19fa64c923cc44b4c5b03216db78bdd2c0e3ff5b&amp;dn=another+super+mario+bros+wbfs&amp;tr=udp%3A%2F%2Ftracker.openbittorrent.com%3A80&amp;tr=udp%3A%2F%2Fopen.demonii.com%3A1337&amp;tr=udp%3A%2F%2Ftracker.coppersurfer.tk%3A6969&amp;tr=udp%3A%2F%2Fexodus.desync.com%3A6969","seeders":2,"leechers":0,"uploader":"gerebenics","files":1,"time":1357020035,"description":"I originally got this file from demiond it is a .wbfs file of another super mario for the wii no need to have original Disk to play this. it will work with usb loaders","torrent":{"xt":"urn:btih:19fa64c923cc44b4c5b03216db78bdd2c0e3ff5b","amp;dn":"another+super+mario+bros+wbfs","amp;tr":["udp%3A%2F%2Ftracker.openbittorrent.com%3A80","udp%3A%2F%2Fopen.demonii.com%3A1337","udp%3A%2F%2Ftracker.coppersurfer.tk%3A6969","udp%3A%2F%2Fexodus.desync.com%3A6969"],"infoHash":"19fa64c923cc44b4c5b03216db78bdd2c0e3ff5b","infoHashBuffer":{"type":"Buffer","data":[25,250,100,201,35,204,68,180,197,176,50,22,219,120,189,210,192,227,255,91]},"announce":[],"urlList":[]}}