{"title":"18 and Japanese #4 - Japanese Porn XXX","uid":8525385,"size":2275019844,"categoryP":"porn","categoryS":"movies","magnet":"?xt=urn:btih:1b2d19eec0460476582a3debfce2b06657279219&amp;dn=18+and+Japanese+%234+-+Japanese+Porn+XXX&amp;tr=udp%3A%2F%2Ftracker.openbittorrent.com%3A80&amp;tr=udp%3A%2F%2Fopen.demonii.com%3A1337&amp;tr=udp%3A%2F%2Ftracker.coppersurfer.tk%3A6969&amp;tr=udp%3A%2F%2Fexodus.desync.com%3A6969","seeders":2,"leechers":0,"uploader":"KidAtomic","files":1,"time":1370017574,"description":"\n18 and Japanese 4: Barely Legal Japanese Girls With Tight, Little Pussies! Our young pussies are ready to get fucked by big hard cocks... Can you fill our holes?\n\nSweet young Japanese teen girls are the order of the day today. When things get a little boring in Tokyo, these girls and guys know how to get out and have a good time. Lots of hairy pussies, cum shots, cock sucking and doggy style going on in this edition of &quot;18 And Japanese&quot;!!!\n\nRating XXX\nReleased Jan 01 2005\nProduction Year 2002\nStudio Oriental Dream Pictures\n\nCAST:\nMiho Aikawa, Noa Tsukishima, Ryoko Serizawa, Yuko Asano\n\n\n","torrent":{"xt":"urn:btih:1b2d19eec0460476582a3debfce2b06657279219","amp;dn":"18+and+Japanese+%234+-+Japanese+Porn+XXX","amp;tr":["udp%3A%2F%2Ftracker.openbittorrent.com%3A80","udp%3A%2F%2Fopen.demonii.com%3A1337","udp%3A%2F%2Ftracker.coppersurfer.tk%3A6969","udp%3A%2F%2Fexodus.desync.com%3A6969"],"infoHash":"1b2d19eec0460476582a3debfce2b06657279219","infoHashBuffer":{"type":"Buffer","data":[27,45,25,238,192,70,4,118,88,42,61,235,252,226,176,102,87,39,146,25]},"announce":[],"urlList":[]}}