{"title":"Backroad.Gold.S01E02.Movie.Car.Madness.HDTV.x264-iTRY","uid":9615954,"size":172772982,"categoryP":"video","categoryS":"tv_shows","magnet":"?xt=urn:btih:2017659cf54d197fdc9962f730458abe1bf9a94b&amp;dn=Backroad.Gold.S01E02.Movie.Car.Madness.HDTV.x264-iTRY&amp;tr=udp%3A%2F%2Ftracker.openbittorrent.com%3A80&amp;tr=udp%3A%2F%2Fopen.demonii.com%3A1337&amp;tr=udp%3A%2F%2Ftracker.coppersurfer.tk%3A6969&amp;tr=udp%3A%2F%2Fexodus.desync.com%3A6969","seeders":2,"leechers":0,"uploader":"LegendET","files":2,"time":1392419280,"description":"src: HDTV\ndur: 21min\ndim: 720x404\nvid: x264\naud: AAC\nbit: VBR\n\t","torrent":{"xt":"urn:btih:2017659cf54d197fdc9962f730458abe1bf9a94b","amp;dn":"Backroad.Gold.S01E02.Movie.Car.Madness.HDTV.x264-iTRY","amp;tr":["udp%3A%2F%2Ftracker.openbittorrent.com%3A80","udp%3A%2F%2Fopen.demonii.com%3A1337","udp%3A%2F%2Ftracker.coppersurfer.tk%3A6969","udp%3A%2F%2Fexodus.desync.com%3A6969"],"infoHash":"2017659cf54d197fdc9962f730458abe1bf9a94b","infoHashBuffer":{"type":"Buffer","data":[32,23,101,156,245,77,25,127,220,153,98,247,48,69,138,190,27,249,169,75]},"announce":[],"urlList":[]}}