{"title":"UDEMY- Full SEO for Website Owners - Boost your Traffic Now!","uid":14028358,"size":1634726136,"categoryP":"other","categoryS":"other","magnet":"?xt=urn:btih:276154b556f373ee8436248dbafd0e3a10d2f047&amp;dn=UDEMY-+Full+SEO+for+Website+Owners+-+Boost+your+Traffic+Now%21&amp;tr=udp%3A%2F%2Ftracker.leechers-paradise.org%3A6969&amp;tr=udp%3A%2F%2Fzer0day.ch%3A1337&amp;tr=udp%3A%2F%2Fopen.demonii.com%3A1337&amp;tr=udp%3A%2F%2Ftracker.coppersurfer.tk%3A6969&amp;tr=udp%3A%2F%2Fexodus.desync.com%3A6969","seeders":2,"leechers":2,"uploader":"Bluetex","files":22,"time":1458943309,"description":"RELEASE NAME:\r\n\r\nFull SEO for Website Owners - Boost your Traffic Now!\r\n\r\n\r\nCourse Description\r\n\r\nI created this course for YOU - entrepreneurs, freelancers, bloggers.\r\n\r\nYou want to make your dreams come true and drive thousands of visitors to your website that will use or buy the service you offer - this is the course for you.\r\n\r\nWhy you should take this course?\r\n\r\nComplete: Everything you need in one place\r\nProfessional: Experienced instructor\r\nSafe: Based on Google Resources (including proofs)\r\nSpecial: Planned and built exactly for your need\r\nHigh quality: High quality sound and video\r\nFun!!!: Techniques you'll enjoy doing\r\nPersonal: Get my private email for any question\r\n\r\n\r\nIn this course I teach how to hack SEO, starting from beginners level to advanced. So it's super relevant for blog owners, business owners and freelancers.\r\n\r\nThe goal of this course is training the basics of SEO in order to boost your ranking with both onpage and offpage strategies, keywords users are searching on Google, data report, and audit your own site for technical SEO optimization aspects.\r\n\r\nIf you don't have web coding experience and you are using Wordpress or Joomla it's ok! I'm teaching how to optimize your website using plugins and extensions like yoast and more","torrent":{"xt":"urn:btih:276154b556f373ee8436248dbafd0e3a10d2f047","amp;dn":"UDEMY-+Full+SEO+for+Website+Owners+-+Boost+your+Traffic+Now%21","amp;tr":["udp%3A%2F%2Ftracker.leechers-paradise.org%3A6969","udp%3A%2F%2Fzer0day.ch%3A1337","udp%3A%2F%2Fopen.demonii.com%3A1337","udp%3A%2F%2Ftracker.coppersurfer.tk%3A6969","udp%3A%2F%2Fexodus.desync.com%3A6969"],"infoHash":"276154b556f373ee8436248dbafd0e3a10d2f047","infoHashBuffer":{"type":"Buffer","data":[39,97,84,181,86,243,115,238,132,54,36,141,186,253,14,58,16,210,240,71]},"announce":[],"urlList":[]}}