{"title":"VLC Media Player v1.1.9 (32-Bit) Full Version - {RedDragon}","uid":6461759,"size":20536631,"categoryP":"applications","categoryS":"windows","magnet":"?xt=urn:btih:27adabd619b2850e41a84c001877c4ee71e0c220&amp;dn=VLC+Media+Player+v1.1.9+%2832-Bit%29+Full+Version+-+%7BRedDragon%7D&amp;tr=udp%3A%2F%2Ftracker.openbittorrent.com%3A80&amp;tr=udp%3A%2F%2Fopen.demonii.com%3A1337&amp;tr=udp%3A%2F%2Ftracker.coppersurfer.tk%3A6969&amp;tr=udp%3A%2F%2Fexodus.desync.com%3A6969","seeders":2,"leechers":0,"uploader":"RedDr4gon","files":3,"time":1307797634,"description":"===============================================\nVLC Media Player \n===============================================\n\n\nNAME :- VLC Media Player .\nSIZE :- 19.5\nPLATFORM :- Windows\nLANGUAGE :- English\nUPLOADER :- RedDragon\nVERSION :- 1.19\n\n\n=================================================\n\n\nSEED AFTER DOWNLAODING .\n\n\n\nTHANK YOU .\n\n\nENjOY .. !!!!!","torrent":{"xt":"urn:btih:27adabd619b2850e41a84c001877c4ee71e0c220","amp;dn":"VLC+Media+Player+v1.1.9+%2832-Bit%29+Full+Version+-+%7BRedDragon%7D","amp;tr":["udp%3A%2F%2Ftracker.openbittorrent.com%3A80","udp%3A%2F%2Fopen.demonii.com%3A1337","udp%3A%2F%2Ftracker.coppersurfer.tk%3A6969","udp%3A%2F%2Fexodus.desync.com%3A6969"],"infoHash":"27adabd619b2850e41a84c001877c4ee71e0c220","infoHashBuffer":{"type":"Buffer","data":[39,173,171,214,25,178,133,14,65,168,76,0,24,119,196,238,113,224,194,32]},"announce":[],"urlList":[]}}