{"title":"Paradise(1991)","uid":6169925,"size":1055357176,"categoryP":"video","categoryS":"movies","magnet":"?xt=urn:btih:377e075034e6763996f8f89a2e19bbc30b5f3ba8&amp;dn=Paradise%281991%29&amp;tr=udp%3A%2F%2Ftracker.openbittorrent.com%3A80&amp;tr=udp%3A%2F%2Fopen.demonii.com%3A1337&amp;tr=udp%3A%2F%2Ftracker.coppersurfer.tk%3A6969&amp;tr=udp%3A%2F%2Fexodus.desync.com%3A6969","seeders":2,"leechers":0,"uploader":"randmize","files":2,"time":1297530040,"description":"Paradise (1991) With Don Johnson and Melanie Griffiths.","torrent":{"xt":"urn:btih:377e075034e6763996f8f89a2e19bbc30b5f3ba8","amp;dn":"Paradise%281991%29","amp;tr":["udp%3A%2F%2Ftracker.openbittorrent.com%3A80","udp%3A%2F%2Fopen.demonii.com%3A1337","udp%3A%2F%2Ftracker.coppersurfer.tk%3A6969","udp%3A%2F%2Fexodus.desync.com%3A6969"],"infoHash":"377e075034e6763996f8f89a2e19bbc30b5f3ba8","infoHashBuffer":{"type":"Buffer","data":[55,126,7,80,52,230,118,57,150,248,248,154,46,25,187,195,11,95,59,168]},"announce":[],"urlList":[]}}