{"title":"Bones.S08E06.HDTV.Subtitulado.Esp.SC.avi","uid":7820899,"size":361553920,"categoryP":"video","categoryS":"tv_shows","magnet":"?xt=urn:btih:39daec48a4f7b82dd1e769ea574f2555c0099d9c&amp;dn=Bones.S08E06.HDTV.Subtitulado.Esp.SC.avi&amp;tr=udp%3A%2F%2Ftracker.openbittorrent.com%3A80&amp;tr=udp%3A%2F%2Fopen.demonii.com%3A1337&amp;tr=udp%3A%2F%2Ftracker.coppersurfer.tk%3A6969&amp;tr=udp%3A%2F%2Fexodus.desync.com%3A6969","seeders":2,"leechers":1,"uploader":"protonotario","files":1,"time":1352817461,"description":"Bones.S08E06.HDTV.Subtitulado.Esp.SC.avi","torrent":{"xt":"urn:btih:39daec48a4f7b82dd1e769ea574f2555c0099d9c","amp;dn":"Bones.S08E06.HDTV.Subtitulado.Esp.SC.avi","amp;tr":["udp%3A%2F%2Ftracker.openbittorrent.com%3A80","udp%3A%2F%2Fopen.demonii.com%3A1337","udp%3A%2F%2Ftracker.coppersurfer.tk%3A6969","udp%3A%2F%2Fexodus.desync.com%3A6969"],"infoHash":"39daec48a4f7b82dd1e769ea574f2555c0099d9c","infoHashBuffer":{"type":"Buffer","data":[57,218,236,72,164,247,184,45,209,231,105,234,87,79,37,85,192,9,157,156]},"announce":[],"urlList":[]}}