{"title":"Kain album","uid":3810908,"size":92772874,"categoryP":"audio","categoryS":"music","magnet":"?xt=urn:btih:4c9b935975d7128c409b9c9ad20c86781084bb29&amp;dn=Kain+album&amp;tr=udp%3A%2F%2Ftracker.openbittorrent.com%3A80&amp;tr=udp%3A%2F%2Fopen.demonii.com%3A1337&amp;tr=udp%3A%2F%2Ftracker.coppersurfer.tk%3A6969&amp;tr=udp%3A%2F%2Fexodus.desync.com%3A6969","seeders":2,"leechers":2,"uploader":"elerico","files":16,"time":1190136277,"description":"New album from kain","torrent":{"xt":"urn:btih:4c9b935975d7128c409b9c9ad20c86781084bb29","amp;dn":"Kain+album","amp;tr":["udp%3A%2F%2Ftracker.openbittorrent.com%3A80","udp%3A%2F%2Fopen.demonii.com%3A1337","udp%3A%2F%2Ftracker.coppersurfer.tk%3A6969","udp%3A%2F%2Fexodus.desync.com%3A6969"],"infoHash":"4c9b935975d7128c409b9c9ad20c86781084bb29","infoHashBuffer":{"type":"Buffer","data":[76,155,147,89,117,215,18,140,64,155,156,154,210,12,134,120,16,132,187,41]},"announce":[],"urlList":[]}}