{"title":"Anissa Kate,Ava Dalush And Suhaila Hard - Orgy By Surprise HD 72","uid":9425489,"size":2539751618,"categoryP":"porn","categoryS":"hd___movies","magnet":"?xt=urn:btih:6b248f5d894e9a23b6842c448ebb0c8c6bb8a23d&amp;dn=Anissa+Kate%2CAva+Dalush+And+Suhaila+Hard+-+Orgy+By+Surprise+HD+72&amp;tr=udp%3A%2F%2Ftracker.openbittorrent.com%3A80&amp;tr=udp%3A%2F%2Fopen.demonii.com%3A1337&amp;tr=udp%3A%2F%2Ftracker.coppersurfer.tk%3A6969&amp;tr=udp%3A%2F%2Fexodus.desync.com%3A6969","seeders":2,"leechers":1,"uploader":"ElitePorn","files":-1,"time":1388680345,"description":"Anissa Kate,Ava Dalush And Suhaila Hard - Orgy By Surprise HD 720p\n------------------------------------------------------------------\n\nScreenshots:\n------------\n &lt;a href=&quot;\nhttp://picturescream.asia/soft/zfe&quot; rel=&quot;nofollow&quot; target=&quot;_NEW&quot;&gt;\nhttp://picturescream.asia/soft/zfe&lt;/a&gt;\n &lt;a href=&quot;\nhttp://picturescream.asia/soft/zfr&quot; rel=&quot;nofollow&quot; target=&quot;_NEW&quot;&gt;\nhttp://picturescream.asia/soft/zfr&lt;/a&gt;\n &lt;a href=&quot;\nhttp://picturescream.asia/soft/zf5&quot; rel=&quot;nofollow&quot; target=&quot;_NEW&quot;&gt;\nhttp://picturescream.asia/soft/zf5&lt;/a&gt;\n &lt;a href=&quot;\nhttp://picturescream.asia/soft/zfL&quot; rel=&quot;nofollow&quot; target=&quot;_NEW&quot;&gt;\nhttp://picturescream.asia/soft/zfL&lt;/a&gt;\n &lt;a href=&quot;\nhttp://picturescream.asia/soft/zfX&quot; rel=&quot;nofollow&quot; target=&quot;_NEW&quot;&gt;\nhttp://picturescream.asia/soft/zfX&lt;/a&gt;\n &lt;a href=&quot;\nhttp://picturescream.asia/soft/zfy&quot; rel=&quot;nofollow&quot; target=&quot;_NEW&quot;&gt;\nhttp://picturescream.asia/soft/zfy&lt;/a&gt;\n &lt;a href=&quot;\nhttp://picturescream.asia/soft/zzI&quot; rel=&quot;nofollow&quot; target=&quot;_NEW&quot;&gt;\nhttp://picturescream.asia/soft/zzI&lt;/a&gt;\n &lt;a href=&quot;\nhttp://picturescream.asia/soft/zzt&quot; rel=&quot;nofollow&quot; target=&quot;_NEW&quot;&gt;\nhttp://picturescream.asia/soft/zzt&lt;/a&gt;\n &lt;a href=&quot;\nhttp://picturescream.asia/soft/zz2&quot; rel=&quot;nofollow&quot; target=&quot;_NEW&quot;&gt;\nhttp://picturescream.asia/soft/zz2&lt;/a&gt;\n\n\nDuration: 01:13:14, Format: mp4, Resolution: 1280x720, Size: 2.365 GB","torrent":{"xt":"urn:btih:6b248f5d894e9a23b6842c448ebb0c8c6bb8a23d","amp;dn":"Anissa+Kate%2CAva+Dalush+And+Suhaila+Hard+-+Orgy+By+Surprise+HD+72","amp;tr":["udp%3A%2F%2Ftracker.openbittorrent.com%3A80","udp%3A%2F%2Fopen.demonii.com%3A1337","udp%3A%2F%2Ftracker.coppersurfer.tk%3A6969","udp%3A%2F%2Fexodus.desync.com%3A6969"],"infoHash":"6b248f5d894e9a23b6842c448ebb0c8c6bb8a23d","infoHashBuffer":{"type":"Buffer","data":[107,36,143,93,137,78,154,35,182,132,44,68,142,187,12,140,107,184,162,61]},"announce":[],"urlList":[]}}