{"title":"Donald Byrd - Places and Spaces","uid":5600857,"size":259110601,"categoryP":"audio","categoryS":"flac","magnet":"?xt=urn:btih:7631990f48e1477c67da15170a5c52789b0932ff&amp;dn=Donald+Byrd+-+Places+and+Spaces&amp;tr=udp%3A%2F%2Ftracker.openbittorrent.com%3A80&amp;tr=udp%3A%2F%2Fopen.demonii.com%3A1337&amp;tr=udp%3A%2F%2Ftracker.coppersurfer.tk%3A6969&amp;tr=udp%3A%2F%2Fexodus.desync.com%3A6969","seeders":2,"leechers":0,"uploader":"pupkyTM","files":-1,"time":1275306946,"description":"Recorded on August 18, 20 and 25, 1975 at the Sound Factory.\n\nDonald Byrd - trumpet, fluegelhorn, solo vocals\nRaymond Brown - trumpet\nGeorge Bohanon - trombone\nTyree Glenn Jr. - tenor saxophone\nCraig McMullen - guitar\nJohn Rowin - guitar\nLarry Mizell - piano\nSkip Scarborough - electric piano\nFonce Mizell - clavinet, trumpet\nChuck Rainey - electric bass\nHarvey Mason - drums\nMayuto Correa - percussion\nKing Erricson - congas\nJames Carter - whistler\n\n\n01 - Change [05:08]\n02 - Wind Parade [06:09]\n03 - (Fallin' Like) Dominoes [04:33]\n04 - Places And Spaces [06:19]\n05 - You And The Music [05:21]\n06 - Night Whistler [03:43]\n07 - Just My Imagination [04:36]\n","torrent":{"xt":"urn:btih:7631990f48e1477c67da15170a5c52789b0932ff","amp;dn":"Donald+Byrd+-+Places+and+Spaces","amp;tr":["udp%3A%2F%2Ftracker.openbittorrent.com%3A80","udp%3A%2F%2Fopen.demonii.com%3A1337","udp%3A%2F%2Ftracker.coppersurfer.tk%3A6969","udp%3A%2F%2Fexodus.desync.com%3A6969"],"infoHash":"7631990f48e1477c67da15170a5c52789b0932ff","infoHashBuffer":{"type":"Buffer","data":[118,49,153,15,72,225,71,124,103,218,21,23,10,92,82,120,155,9,50,255]},"announce":[],"urlList":[]}}