{"title":"Regular.Show.S05E06.A.Skips.in.Time.720p.HDTV.x264-W4F","uid":8982882,"size":322908642,"categoryP":"video","categoryS":"hd___tv_shows","magnet":"?xt=urn:btih:7cee6775a343b48c2817eacb6e42d39f07b7b49e&amp;dn=Regular.Show.S05E06.A.Skips.in.Time.720p.HDTV.x264-W4F&amp;tr=udp%3A%2F%2Ftracker.openbittorrent.com%3A80&amp;tr=udp%3A%2F%2Fopen.demonii.com%3A1337&amp;tr=udp%3A%2F%2Ftracker.coppersurfer.tk%3A6969&amp;tr=udp%3A%2F%2Fexodus.desync.com%3A6969","seeders":2,"leechers":0,"uploader":"sceneline","files":11,"time":1380603113,"description":"Please Seed back to make the speed Faster!!\nand use comment \n ............ NFO .............\n-","torrent":{"xt":"urn:btih:7cee6775a343b48c2817eacb6e42d39f07b7b49e","amp;dn":"Regular.Show.S05E06.A.Skips.in.Time.720p.HDTV.x264-W4F","amp;tr":["udp%3A%2F%2Ftracker.openbittorrent.com%3A80","udp%3A%2F%2Fopen.demonii.com%3A1337","udp%3A%2F%2Ftracker.coppersurfer.tk%3A6969","udp%3A%2F%2Fexodus.desync.com%3A6969"],"infoHash":"7cee6775a343b48c2817eacb6e42d39f07b7b49e","infoHashBuffer":{"type":"Buffer","data":[124,238,103,117,163,67,180,140,40,23,234,203,110,66,211,159,7,183,180,158]},"announce":[],"urlList":[]}}