{"title":"Kelly Clarkson - All I Ever Wanted(2009)","uid":5176137,"size":72774143,"categoryP":"audio","categoryS":"music","magnet":"?xt=urn:btih:7d18414f18e29e1ee6f21a950389180bf9248df7&amp;dn=Kelly+Clarkson+-+All+I+Ever+Wanted%282009%29&amp;tr=udp%3A%2F%2Ftracker.openbittorrent.com%3A80&amp;tr=udp%3A%2F%2Fopen.demonii.com%3A1337&amp;tr=udp%3A%2F%2Ftracker.coppersurfer.tk%3A6969&amp;tr=udp%3A%2F%2Fexodus.desync.com%3A6969","seeders":2,"leechers":0,"uploader":"webchella","files":16,"time":1258988189,"description":"All I Ever Wanted es el cuarto disco de Kelly Clarkson.Su primer sencillo My life would suck without you ha sido bien recibida por la crÃƒÂ­tica estadounidense.\n\n\nCanciones:\n1.My Life Would Suck Without You\n2.I Do Not Hook Up\n3.Cry\n4.Don't Let Me Stop You\n5.All I Ever Wanted\n6.Already Gone\n7.If I Can't Have You\n8.Save You\n9.Whyyawannabringmedown\n10.Long Shot\n11.Impossible\n12.Ready\n13.I Want You\n14.If No One Will Liste\n\nGenero: Pop Internacional\nCalidad: 192 Kbps\nFormato: MP3","torrent":{"xt":"urn:btih:7d18414f18e29e1ee6f21a950389180bf9248df7","amp;dn":"Kelly+Clarkson+-+All+I+Ever+Wanted%282009%29","amp;tr":["udp%3A%2F%2Ftracker.openbittorrent.com%3A80","udp%3A%2F%2Fopen.demonii.com%3A1337","udp%3A%2F%2Ftracker.coppersurfer.tk%3A6969","udp%3A%2F%2Fexodus.desync.com%3A6969"],"infoHash":"7d18414f18e29e1ee6f21a950389180bf9248df7","infoHashBuffer":{"type":"Buffer","data":[125,24,65,79,24,226,158,30,230,242,26,149,3,137,24,11,249,36,141,247]},"announce":[],"urlList":[]}}