{"title":"LH - Alison Faye - My Black Stepdaddy Disciplined Me *May 12*","uid":10135907,"size":426298620,"categoryP":"porn","categoryS":"movie_clips","magnet":"?xt=urn:btih:9703437007d11382a4e34fb925f4d65b3187465b&amp;dn=LH+-+Alison+Faye+-+My+Black+Stepdaddy+Disciplined+Me+%2AMay+12%2A&amp;tr=udp%3A%2F%2Ftracker.openbittorrent.com%3A80&amp;tr=udp%3A%2F%2Fopen.demonii.com%3A1337&amp;tr=udp%3A%2F%2Ftracker.coppersurfer.tk%3A6969&amp;tr=udp%3A%2F%2Fexodus.desync.com%3A6969","seeders":2,"leechers":0,"uploader":"nwpornup","files":1,"time":1399944445,"description":" &lt;a href=&quot;http://imgfun.biz/img-5371588f4a037.html&quot; rel=&quot;nofollow&quot; target=&quot;_NEW&quot;&gt;http://imgfun.biz/img-5371588f4a037.html&lt;/a&gt;\n","torrent":{"xt":"urn:btih:9703437007d11382a4e34fb925f4d65b3187465b","amp;dn":"LH+-+Alison+Faye+-+My+Black+Stepdaddy+Disciplined+Me+%2AMay+12%2A","amp;tr":["udp%3A%2F%2Ftracker.openbittorrent.com%3A80","udp%3A%2F%2Fopen.demonii.com%3A1337","udp%3A%2F%2Ftracker.coppersurfer.tk%3A6969","udp%3A%2F%2Fexodus.desync.com%3A6969"],"infoHash":"9703437007d11382a4e34fb925f4d65b3187465b","infoHashBuffer":{"type":"Buffer","data":[151,3,67,112,7,209,19,130,164,227,79,185,37,244,214,91,49,135,70,91]},"announce":[],"urlList":[]}}