{"title":"Race 07 - MOD - DTM 2013","uid":9556300,"size":118830897,"categoryP":"games","categoryS":"pc","magnet":"?xt=urn:btih:af63533a0f7e1e11cbed545244c7e93aa3444783&amp;dn=Race+07+-+MOD+-+DTM+2013&amp;tr=udp%3A%2F%2Ftracker.openbittorrent.com%3A80&amp;tr=udp%3A%2F%2Fopen.demonii.com%3A1337&amp;tr=udp%3A%2F%2Ftracker.coppersurfer.tk%3A6969&amp;tr=udp%3A%2F%2Fexodus.desync.com%3A6969","seeders":2,"leechers":0,"uploader":null,"files":1,"time":1391363491,"description":"Mod DTM 2013 para Race 07 y GTR EVO. Pot Mogh &amp; Print\n\nExtraer en la carpeta del juego\n\nExtract to game folder","torrent":{"xt":"urn:btih:af63533a0f7e1e11cbed545244c7e93aa3444783","amp;dn":"Race+07+-+MOD+-+DTM+2013","amp;tr":["udp%3A%2F%2Ftracker.openbittorrent.com%3A80","udp%3A%2F%2Fopen.demonii.com%3A1337","udp%3A%2F%2Ftracker.coppersurfer.tk%3A6969","udp%3A%2F%2Fexodus.desync.com%3A6969"],"infoHash":"af63533a0f7e1e11cbed545244c7e93aa3444783","infoHashBuffer":{"type":"Buffer","data":[175,99,83,58,15,126,30,17,203,237,84,82,68,199,233,58,163,68,71,131]},"announce":[],"urlList":[]}}