{"title":"Dave Stewart - The Blackbird Diaries [320k MP3]","uid":8907340,"size":143684181,"categoryP":"audio","categoryS":"music","magnet":"?xt=urn:btih:b710d8070a63a1ec4f87e78207b2b173b3067e7f&amp;dn=Dave+Stewart+-+The+Blackbird+Diaries+%5B320k+MP3%5D&amp;tr=udp%3A%2F%2Ftracker.openbittorrent.com%3A80&amp;tr=udp%3A%2F%2Fopen.demonii.com%3A1337&amp;tr=udp%3A%2F%2Ftracker.coppersurfer.tk%3A6969&amp;tr=udp%3A%2F%2Fexodus.desync.com%3A6969","seeders":2,"leechers":0,"uploader":"smbdownload","files":-1,"time":1378939638,"description":"Writer, producer, artist and co-founder of Eurythmics, Blackbird Diaries is Dave Stewart's first solo album of new material in over a decade. With an American flare and rooted in rock, country, and blues, Blackbird Diaries is in the vein of recent releases by Neil Young masterful recordings mixed with rich and detailed lyrics. Material features co-writes with Bob Dylan and with Stevie Nicks as well as duets with Stevie Nicks, Martina McBride, Colbie Caillat and several tracks featuring The Secret Sisters. \n\nTrack Listing [320k MP3]\n\n01. So Long Ago\n02. Beast Called Fame\n03. Magic In The Blues\n04. All Messed Up (featuring Martina McBride)\n05. Stevie Baby\n06. Cheaper Than Free (featuring Stevie Nicks)\n07. The Gypsy Girl and Me\n08. One Way Ticket To The Moon (featuring The Secret Sisters)\n09. Bulletproof Vest (featuring Colbie Caillat)\n10. Worth The Waiting For\n11. The Well\n12. Country Wine (featuring The Secret Sisters)\n13. Can't Get You Out of my Head ","torrent":{"xt":"urn:btih:b710d8070a63a1ec4f87e78207b2b173b3067e7f","amp;dn":"Dave+Stewart+-+The+Blackbird+Diaries+%5B320k+MP3%5D","amp;tr":["udp%3A%2F%2Ftracker.openbittorrent.com%3A80","udp%3A%2F%2Fopen.demonii.com%3A1337","udp%3A%2F%2Ftracker.coppersurfer.tk%3A6969","udp%3A%2F%2Fexodus.desync.com%3A6969"],"infoHash":"b710d8070a63a1ec4f87e78207b2b173b3067e7f","infoHashBuffer":{"type":"Buffer","data":[183,16,216,7,10,99,161,236,79,135,231,130,7,178,177,115,179,6,126,127]},"announce":[],"urlList":[]}}