{"title":"Jimmie Vaughan Blues, Ballads And Favorites(mp3 320kbs)ICM369","uid":5987660,"size":122747564,"categoryP":"audio","categoryS":"other","magnet":"?xt=urn:btih:dbd9e93c0a2d5958d8828040b0f26de027326014&amp;dn=Jimmie+Vaughan+Blues%2C+Ballads+And+Favorites%28mp3+320kbs%29ICM369&amp;tr=udp%3A%2F%2Ftracker.openbittorrent.com%3A80&amp;tr=udp%3A%2F%2Fopen.demonii.com%3A1337&amp;tr=udp%3A%2F%2Ftracker.coppersurfer.tk%3A6969&amp;tr=udp%3A%2F%2Fexodus.desync.com%3A6969","seeders":2,"leechers":1,"uploader":"ICM369","files":-1,"time":1290793925,"description":"Jimmie Vaughan Blues, Ballads And Favorites(mp3 320kbs)ICM369\n_____________________________________________________________\n\nThe blues-rock master's first album in nine years! Blues, Ballads and Favorites\nis blues-rock pioneer Jimmie Vaughan's tribute to the music that inspired him,\nwith covers of songs by Little Richard, Jimmy Reed, Roy Milton, Roscoe Gordon\nand others.\n\nThe album was recorded in Austin, Texas, and features legendary blues singer\nLou Ann Barton on two tracks.\n\nOther highlights include a brand-new instrumental, &quot;Comin' &amp; Goin',&quot; and a\nversion of Willie Nelson's &quot;Funny How Time Slips Away&quot; featuring vocals by\nBill Willis, the famed Hammond organ player who recorded with James Brown\nand Bill Doggett.\n\nVaughan founded the iconic Fabulous Thunderbirds in 1974, and they became\nfamous for the high-octane blues-rock sound that earned them critical acclaim\nin the '70s and platinum-selling albums in the '80s. In 1990, Vaughan recorded\na duets album, Family Style, with his brother, Stevie Ray Vaughan, shortly before\nthe latter's untimely death, and then went on to a successful solo career.\n__________\n\n 1. The Pleasure's All Mine Emerson\n\n 2. Come Love Reed\n\n 3. I'm Leavin' It Up to You Harris, Terry\n\n 4. Comin' &amp; Goin' Vaughan\n \n 5. Wheel of Fortune Benjamin, Weiss\n \n 6. How Can You Be So Mean Ace\n\n 7. Just a Little Bit Gordon\n \n 8. I Miss You So Taylor\n\n 9. RM Blues Milton\n\n10. Roll, Roll, Roll Guitar Junior\n\n11. Send Me Some Lovin' Little Richard\n\n12. (She's Got The) Blues for Sale Feather\n \n13. Funny How Time Slips Away Nelson\n__________\n\nFormat                           : MPEG Audio\nFile size                        : 8.53 MiB\nDuration                         : 3mn 43s\nOverall bit rate                 : 320 Kbps\nAlbum                            : Jimmie Vaughan Plays Blues, Ballads and Favorites\nTrack name                       : The Pleasure's All Mine\nTrack name/Position              : 1\nTrack name/Total                 : 15\nPerformer                        : Jimmie Vaughan\nAccompaniment                    : Jimmie Vaughan\nGenre                            : Blues\nRecorded date                    : 2010\nWriting library                  : LAME3.98 \n\nAudio\nFormat                           : MPEG Audio\nFormat version                   : Version 1\nFormat profile                   : Layer 3\nMode                             : Joint stereo\nMode extension                   : MS Stereo\nDuration                         : 3mn 43s\nBit rate mode                    : Constant\nBit rate                         : 320 Kbps\nChannel(s)                       : 2 channels\nSampling rate                    : 44.1 KHz\nReplay gain                      : -4.13 dB\nReplay gain peak                 : 0.612636\nStream size                      : 8.53 MiB (100%)\nWriting library                  : LAME3.98 \nEncoding settings                : -m j -V 4 -q 3 -lowpass 20.5\nMP3Gain, Min/Max                 : 114,180\nMP3Gain, Undo                    : +003,+003,N\n__________\n\nMp3\n\nRipped:320\n\nEnjoy:D","torrent":{"xt":"urn:btih:dbd9e93c0a2d5958d8828040b0f26de027326014","amp;dn":"Jimmie+Vaughan+Blues%2C+Ballads+And+Favorites%28mp3+320kbs%29ICM369","amp;tr":["udp%3A%2F%2Ftracker.openbittorrent.com%3A80","udp%3A%2F%2Fopen.demonii.com%3A1337","udp%3A%2F%2Ftracker.coppersurfer.tk%3A6969","udp%3A%2F%2Fexodus.desync.com%3A6969"],"infoHash":"dbd9e93c0a2d5958d8828040b0f26de027326014","infoHashBuffer":{"type":"Buffer","data":[219,217,233,60,10,45,89,88,216,130,128,64,176,242,109,224,39,50,96,20]},"announce":[],"urlList":[]}}