{"title":"[LatinaSexTapes] Marsha May (Blonde Gamer Rides Cock - 13.04.16)","uid":14309981,"size":334192254,"categoryP":"porn","categoryS":"movie_clips","magnet":"?xt=urn:btih:f1eb4a005342d4eb8d6521f2c76a1564cfbc36d8&amp;dn=%5BLatinaSexTapes%5D+Marsha+May+%28Blonde+Gamer+Rides+Cock+-+13.04.16%29&amp;tr=udp%3A%2F%2Ftracker.leechers-paradise.org%3A6969&amp;tr=udp%3A%2F%2Fzer0day.ch%3A1337&amp;tr=udp%3A%2F%2Fopen.demonii.com%3A1337&amp;tr=udp%3A%2F%2Ftracker.coppersurfer.tk%3A6969&amp;tr=udp%3A%2F%2Fexodus.desync.com%3A6969","seeders":2,"leechers":1,"uploader":"KayWily","files":1,"time":1460530137,"description":"[LatinaSexTapes] Marsha May (Blonde Gamer Rides Cock - 13.04.16)\r\n\r\n \nhttp://porn-harbor.com/image/NK8","torrent":{"xt":"urn:btih:f1eb4a005342d4eb8d6521f2c76a1564cfbc36d8","amp;dn":"%5BLatinaSexTapes%5D+Marsha+May+%28Blonde+Gamer+Rides+Cock+-+13.04.16%29","amp;tr":["udp%3A%2F%2Ftracker.leechers-paradise.org%3A6969","udp%3A%2F%2Fzer0day.ch%3A1337","udp%3A%2F%2Fopen.demonii.com%3A1337","udp%3A%2F%2Ftracker.coppersurfer.tk%3A6969","udp%3A%2F%2Fexodus.desync.com%3A6969"],"infoHash":"f1eb4a005342d4eb8d6521f2c76a1564cfbc36d8","infoHashBuffer":{"type":"Buffer","data":[241,235,74,0,83,66,212,235,141,101,33,242,199,106,21,100,207,188,54,216]},"announce":[],"urlList":[]}}