{"title":"Nick Thayer &amp; Tommy Lee feat. Sofi &amp;ndash; Middlefingah (201","uid":10841955,"size":7653786,"categoryP":"audio","categoryS":"music","magnet":"?xt=urn:btih:fb390c2d86f7c965b4e89a013b8fc5ba7f1e6737&amp;dn=Nick+Thayer+%26amp%3B+Tommy+Lee+feat.+Sofi+%26ndash%3B+Middlefingah+%28201&amp;tr=udp%3A%2F%2Ftracker.openbittorrent.com%3A80&amp;tr=udp%3A%2F%2Fopen.demonii.com%3A1337&amp;tr=udp%3A%2F%2Ftracker.coppersurfer.tk%3A6969&amp;tr=udp%3A%2F%2Fexodus.desync.com%3A6969","seeders":2,"leechers":0,"uploader":"RG.REBOOT","files":-1,"time":1408744468,"description":"Artist       : Nick Thayer &amp; Tommy Lee\nAlbum        : Middlefingah\nGenre        : Trap\nYear         : 2014\nTracks       : 1\nPlaytime     : 00:03:09\nSize         : 7.27 MB\nCodec        : MPEG 1 Layer III / Lame 3.98 / 320 kbps\n\n01. Middlefingah (feat. Sofi) (03:09)","torrent":{"xt":"urn:btih:fb390c2d86f7c965b4e89a013b8fc5ba7f1e6737","amp;dn":"Nick+Thayer+%26amp%3B+Tommy+Lee+feat.+Sofi+%26ndash%3B+Middlefingah+%28201","amp;tr":["udp%3A%2F%2Ftracker.openbittorrent.com%3A80","udp%3A%2F%2Fopen.demonii.com%3A1337","udp%3A%2F%2Ftracker.coppersurfer.tk%3A6969","udp%3A%2F%2Fexodus.desync.com%3A6969"],"infoHash":"fb390c2d86f7c965b4e89a013b8fc5ba7f1e6737","infoHashBuffer":{"type":"Buffer","data":[251,57,12,45,134,247,201,101,180,232,154,1,59,143,197,186,127,30,103,55]},"announce":[],"urlList":[]}}